prs_commons/__init__.py
prs_commons/__version__.py
prs_commons/core.py
prs_commons/aws/__init__.py
prs_commons/aws/s3_client.py
prs_commons/db/__init__.py
prs_commons/db/base.py
prs_commons/db/postgres_client.py
prs_commons/db/postgres_connection.py
prs_commons/odoo/rpc_client.py
prs_commons/storage/base.py
prs_commons/storage/bucket.py
prs_commons-0.2.8.dist-info/licenses/LICENSE
prs_commons-0.2.8.dist-info/METADATA
prs_commons-0.2.8.dist-info/WHEEL
prs_commons-0.2.8.dist-info/entry_points.txt
prs_commons-0.2.8.dist-info/top_level.txt
prs_commons-0.2.8.dist-info/RECORD
